magic_profanity/__init__.py
magic_profanity/constants.py
magic_profanity/enhancement.py
magic_profanity/magic_profanity.py
magic_profanity/sentiment.py
magic_profanity/unicode.json
magic_profanity/utils.py
magic_profanity/variant.py
magic_profanity/wordlist.txt
magic_profanity/__pycache__/__init__.cpython-38.pyc
magic_profanity/__pycache__/constants.cpython-38.pyc
magic_profanity/__pycache__/magic_profanity.cpython-38.pyc
magic_profanity/__pycache__/utils.cpython-38.pyc
magic_profanity/__pycache__/variant.cpython-38.pyc
magic_profanity-2.0.1.dist-info/licenses/LICENSE
test/__init__.py
test/test_magic_profanity.py
magic_profanity-2.0.1.dist-info/METADATA
magic_profanity-2.0.1.dist-info/WHEEL
magic_profanity-2.0.1.dist-info/top_level.txt
magic_profanity-2.0.1.dist-info/RECORD
