Metadata-Version: 2.4
Name: magic_profanity
Version: 2.0.1
Summary: A Python library for detecting and censoring profanity in text
Home-page: https://github.com/Kabhishek18/magic_profanity
Author: Kumar Abhishek
Author-email: developer@kabhishek18.com
Keywords: profanity-filter censorship text-processing
Classifier: Development Status :: 5 - Production/Stable
Classifier: Intended Audience :: Developers
Classifier: License :: OSI Approved :: MIT License
Classifier: Programming Language :: Python :: 3
Classifier: Programming Language :: Python :: 3.9
Classifier: Programming Language :: Python :: Implementation :: PyPy
Classifier: Operating System :: OS Independent
Requires-Python: >=3.9
License-File: LICENSE
Requires-Dist: nltk>=3.6.0
Dynamic: author
Dynamic: author-email
Dynamic: classifier
Dynamic: description
Dynamic: description-content-type
Dynamic: home-page
Dynamic: keywords
Dynamic: license-file
Dynamic: requires-dist
Dynamic: requires-python
Dynamic: summary
